{
  "responseHeader":{
    "status":0,
    "QTime":483,
    "params":{
      "facet":"true",
      "facet.mincount":"1",
      "indent":"true",
      "q":"hash:\"sha1:FWXKVC27DHYLYIE5S5WAFPLKZNI3ACYK\"",
      "facet.field":"domain",
      "wt":"json",
      "fq":"crawl_years:2009",
      "rows":"1"}},
  "response":{"numFound":2864,"start":0,"maxScore":10.305121,"docs":[
      {
        "source_file_s":"DOTUK-HISTORICAL-1996-2010-GROUP-AN-XABCWD-20110428000000-00000.arc.gz@65785531",
        "url":"http://www.pydw.co.uk/images/spacer.gif",
        "content_type_ext":"gif",
        "host":"www.pydw.co.uk",
        "domain":"pydw.co.uk",
        "public_suffix":"co.uk",
        "server":["Apache/1.3.33 (Debian GNU/Linux) PHP/4.3.10-16 mod_ssl/2.8.22 OpenSSL/0.9.7e"],
        "content_type_served":"image/gif",
        "content_length":43,
        "id":"sha1:FWXKVC27DHYLYIE5S5WAFPLKZNI3ACYK/A2D+MPuBB9jhwhaVSjYl9w==",
        "hash":["sha1:FWXKVC27DHYLYIE5S5WAFPLKZNI3ACYK"],
        "crawl_dates":["2009-10-22T15:12:12Z",
          "2007-10-31T03:36:06Z"],
        "crawl_years":["2009",
          "2007"],
        "crawl_date":"2007-10-31T03:36:06Z",
        "crawl_year":"2007",
        "wayback_date":"20071031033606",
        "content":[""],
        "content_text_length":0,
        "content_metadata_ss":["Compression Lossless=true",
          "width=1",
          "Dimension ImageOrientation=Normal",
          "Compression CompressionTypeName=lzw",
          "Dimension HorizontalPixelOffset=0",
          "tiff:ImageLength=1",
          "Data SampleFormat=Index",
          "ImageDescriptor=imageLeftPosition=0, imageTopPosition=0, imageWidth=1, imageHeight=1, interlaceFlag=false",
          "height=1",
          "Chroma NumChannels=4",
          "Compression NumProgressiveScans=1",
          "Chroma ColorSpaceType=RGB",
          "tiff:ImageWidth=1",
          "Transparency TransparentIndex=0",
          "Chroma BlackIsZero=true",
          "GraphicControlExtension=disposalMethod=none, userInputFlag=false, transparentColorFlag=true, delayTime=0, transparentColorIn",
          "Dimension VerticalPixelOffset=0"],
        "content_type":["image/gif"],
        "content_ffb":"47494638",
        "content_first_bytes":"47 49 46 38 39 61 01 00 01 00 80 00 00 ff ff ff 00 00 00 21 f9 04 01 00 00 00 00 2c 00 00 00 00",
        "content_type_droid":"image/gif; version=89a",
        "content_type_tika":"image/gif",
        "content_type_version":"89a",
        "content_type_full":"image/gif; version=89a",
        "content_type_norm":"image",
        "_version_":1474050072581767168}]
  },
  "facet_counts":{
    "facet_queries":{},
    "facet_fields":{
      "domain":[
        "feedburner.com",962,
        "timesonline.co.uk",471,
        "bbc.co.uk",79,
        "yahoo.com",66,
        "free-counters.co.uk",61,
        "doubleclick.net",42,
        "ixnp.com",32,
        "channelweb.co.uk",23,
        "feedsportal.com",23,
        "engadget.com",19,
        "yimg.com",18,
        "sitestat.com",15,
        "networksolutions.com",14,
        "free-counter.co.uk",13,
        "google.com",11,
        "aol.com",10,
        "searchenginewatch.com",8,
        "leeds.gov.uk",7,
        "ucl.ac.uk",7,
        "londonsummit.gov.uk",6,
        "misco.co.uk",6,
        "nationalgeographic.com",6,
        "netclime.net",6,
        "myspace.com",5,
        "next.co.uk",5,
        "fastclick.net",4,
        "gameduell.de",4,
        "okcupid.com",4,
        "rhul.ac.uk",4,
        "thunderstats.com",4,
        "adorama.com",3,
        "asthma.org.uk",3,
        "bloomberg.com",3,
        "britishsugar.co.uk",3,
        "carnival.com",3,
        "clarion.com",3,
        "constantcontact.com",3,
        "direct2drive.co.uk",3,
        "domeus.com",3,
        "ecrater.com",3,
        "fco.gov.uk",3,
        "flooble.com",3,
        "freecom.com",3,
        "herts.sch.uk",3,
        "ian.com",3,
        "ifpn.org.uk",3,
        "images-amazon.com",3,
        "jobjourney.co.uk",3,
        "kaspersky.com",3,
        "kompressorz.co.uk",3,
        "lastminute.com",3,
        "lutron.com",3,
        "maplin.co.uk",3,
        "mfcreative.com",3,
        "monster.com",3,
        "myspacecdn.com",3,
        "netvibes.com",3,
        "siemens.co.uk",3,
        "thesun.co.uk",3,
        "whitbygazette.co.uk",3,
        "whsmith.co.uk",3,
        "www.bl.uk",3,
        "www.nls.uk",3,
        "wysg.co.uk",3,
        "abeeco.co.uk",2,
        "abingdongymclub.co.uk",2,
        "acmedsci.ac.uk",2,
        "adbrite.com",2,
        "airnewzealand.co.nz",2,
        "allmoviephoto.com",2,
        "amazon.com",2,
        "amazonservices.com",2,
        "andale.com",2,
        "answers.com",2,
        "anytimefitness.com",2,
        "art.com",2,
        "asianews.it",2,
        "banbridgeleader.co.uk",2,
        "barrheadtravel.co.uk",2,
        "bcy.ca",2,
        "bham.ac.uk",2,
        "bianchi.com",2,
        "blackpoolgazette.co.uk",2,
        "blogger.com",2,
        "boscoclc.org.uk",2,
        "bravenet.com",2,
        "bronto.com",2,
        "caterham.co.uk",2,
        "cfo.com",2,
        "channeladvisor.com",2,
        "chiefs.co.uk",2,
        "clickview.co.uk",2,
        "clinicalguard.com",2,
        "cmpnet.com",2,
        "coolspacetricks.com",2,
        "covermore.co.uk",2,
        "crazydomains.com.au",2,
        "dealers-landrover.co.uk",2,
        "decathlon.co.uk",2,
        "derbyshiretimes.co.uk",2]},
    "facet_dates":{},
    "facet_ranges":{}}}
