{
  "responseHeader":{
    "status":0,
    "QTime":653,
    "params":{
      "facet":"true",
      "facet.mincount":"1",
      "indent":"true",
      "q":"hash:\"sha1:TUA4YXOI4BBMBVFNNT5YWOWDR2CKL347\"",
      "facet.field":"domain",
      "wt":"json",
      "fq":"crawl_years:2005",
      "rows":"1"}},
  "response":{"numFound":852,"start":0,"maxScore":12.162724,"docs":[
      {
        "source_file_s":"DOTUK-HISTORICAL-1996-2010-GROUP-AD-XAAWVN-20110428000000-00000.arc.gz@53215026",
        "url":"http://www.assoc-amazon.co.uk:80/e/ir?t=ramcom-21&amp;l=as2&amp;o=2&amp;a=1861002254",
        "host":"www.assoc-amazon.co.uk",
        "domain":"assoc-amazon.co.uk",
        "public_suffix":"co.uk",
        "content_type_served":"image/gif",
        "content_length":42,
        "id":"sha1:TUA4YXOI4BBMBVFNNT5YWOWDR2CKL347/5PmL+kXIokjjt+V1fkHjxw==",
        "hash":["sha1:TUA4YXOI4BBMBVFNNT5YWOWDR2CKL347"],
        "crawl_dates":["2006-01-14T15:22:30Z",
          "2006-02-10T16:17:39Z",
          "2005-12-20T06:53:49Z"],
        "crawl_years":["2006",
          "2006",
          "2005"],
        "crawl_date":"2005-12-20T06:53:49Z",
        "crawl_year":"2005",
        "wayback_date":"20051220065349",
        "content":[""],
        "content_text_length":0,
        "content_metadata_ss":["Compression Lossless=true",
          "width=1",
          "Dimension ImageOrientation=Normal",
          "Compression CompressionTypeName=lzw",
          "Dimension HorizontalPixelOffset=0",
          "tiff:ImageLength=1",
          "Data SampleFormat=Index",
          "ImageDescriptor=imageLeftPosition=0, imageTopPosition=0, imageWidth=1, imageHeight=1, interlaceFlag=true",
          "height=1",
          "Chroma NumChannels=4",
          "Compression NumProgressiveScans=4",
          "Chroma ColorSpaceType=RGB",
          "tiff:ImageWidth=1",
          "Transparency TransparentIndex=0",
          "Chroma BlackIsZero=true",
          "GraphicControlExtension=disposalMethod=none, userInputFlag=false, transparentColorFlag=true, delayTime=0, transparentColorIn",
          "Dimension VerticalPixelOffset=0"],
        "content_type":["image/gif"],
        "content_ffb":"47494638",
        "content_first_bytes":"47 49 46 38 39 61 01 00 01 00 80 00 00 00 00 00 ff ff ff 21 f9 04 01 00 00 00 00 2c 00 00 00 00",
        "content_type_droid":"image/gif; version=89a",
        "content_type_tika":"image/gif",
        "content_type_version":"89a",
        "content_type_full":"image/gif; version=89a",
        "content_type_norm":"image",
        "_version_":1473794955317084160}]
  },
  "facet_counts":{
    "facet_queries":{},
    "facet_fields":{
      "domain":[
        "assoc-amazon.co.uk",615,
        "force9.co.uk",37,
        "assoc-amazon.com",20,
        "globalvision.co.uk",6,
        "gltc.co.uk",6,
        "astrocentre.co.uk",5,
        "londontown.com",5,
        "msn.com",4,
        "assoc-amazon.ca",3,
        "freeserve.co.uk",3,
        "assoc-amazon.jp",2,
        "bbc.co.uk",2,
        "btinternet.co.uk",2,
        "classictractormagazine.co.uk",2,
        "divernet.com",2,
        "diypromotion.co.uk",2,
        "ferrariownersclub.co.uk",2,
        "free-online.co.uk",2,
        "gftu.org.uk",2,
        "lineafashion.com",2,
        "logocrystal.co.uk",2,
        "london-taxi.co.uk",2,
        "nccmembership.co.uk",2,
        "redpepper.org.uk",2,
        "rhbnc.ac.uk",2,
        "stockauditor.co.uk",2,
        "sundialmagazines.co.uk",2,
        "themortgagecalc.co.uk",2,
        "totallyairports.com",2,
        "washingtongreen.co.uk",2,
        "21up.co.uk",1,
        "53a-pix.co.uk",1,
        "adtel.co.uk",1,
        "ajneal.co.uk",1,
        "alinda.co.uk",1,
        "angelcontrols.co.uk",1,
        "assoc-amazon.de",1,
        "assoc-amazon.fr",1,
        "atexmiles.co.uk",1,
        "babesonly.co.uk",1,
        "bengalcatclub.co.uk",1,
        "bestbizopp.co.uk",1,
        "blandfordscouts.org.uk",1,
        "boob.co.uk",1,
        "borussiaboots.co.uk",1,
        "bradburygallery.co.uk",1,
        "bsac-em.org.uk",1,
        "bsacforum.co.uk",1,
        "bsacsnorkelling.co.uk",1,
        "bsactravelclub.co.uk",1,
        "ca-mediaproducts.co.uk",1,
        "cam.ac.uk",1,
        "careerlinkcv.co.uk",1,
        "carmechanicsmag.co.uk",1,
        "carnevalerestaurant.co.uk",1,
        "clanuk2.co.uk",1,
        "claritysupport.co.uk",1,
        "cmvmag.co.uk",1,
        "completecomms.co.uk",1,
        "courseworkbank.co.uk",1,
        "cpmmag.co.uk",1,
        "croydonbsac.co.uk",1,
        "cvcmag.co.uk",1,
        "darlen.co.uk",1,
        "dataseekers.co.uk",1,
        "demon.co.uk",1,
        "doggieville.co.uk",1,
        "eastlothiandivers.org.uk",1,
        "eclipse.co.uk",1,
        "ecott.org.uk",1,
        "estateangels.co.uk",1,
        "farmtrails.org.uk",1,
        "felinbach.org.uk",1,
        "flushingloo.co.uk",1,
        "ford-granadaguild.org.uk",1,
        "fsbusiness.co.uk",1,
        "gimlet.co.uk",1,
        "grassrootsfootball.org.uk",1,
        "gunsandgirls.co.uk",1,
        "halcyon.co.uk",1,
        "hampers-of-cambridge.co.uk",1,
        "immortalvirus.co.uk",1,
        "jedisparadise.co.uk",1,
        "joomladesigns.co.uk",1,
        "jupiteradvertising.co.uk",1,
        "kelsey-accessories.co.uk",1,
        "kent.sch.uk",1,
        "kingbeam.co.uk",1,
        "logogolf.co.uk",1,
        "logoluggage.co.uk",1,
        "lurch.org.uk",1,
        "lycos.co.uk",1,
        "lyndongraey.co.uk",1,
        "mambodesign.co.uk",1,
        "mcc.ac.uk",1,
        "mercedesenthusiast.co.uk",1,
        "mylondon.co.uk",1,
        "nationaltractorshow.co.uk",1,
        "nethosted.co.uk",1,
        "newsnow.co.uk",1]},
    "facet_dates":{},
    "facet_ranges":{}}}
